Workbook

Sheet Parâmetros
A1: RV ENGENHARIA — CONTROLE DE DIÁRIAS E CUSTOS
A2: Obra: Selecta – Gil Martins · Av. Gil Martins, 3144 – Três Andares – Teresina/PI · RV Engenharia
A4: Semana de referência | C4: 46223 | D4: a | E4: 46228
A6: EQUIPE E VALORES DE DIÁRIA
A7: Funcionário | B7: Função | C7: Diária (R$) | D7: Situação
A8: Thiago | B8: Pedreiro | C8: 200 | D8: Ativo
A9: Wiliton | B9: Eletricista | C9: 200 | D9: Ativo
A10: Gervasio | B10: Ajudante | C10: 90 | D10: Desligado em 29/07
A11: Máximo | B11: Ajudante | C11: 100 | D11: Ativo
A12: Amigo Máximo | B12: Ajudante | C12: 100 | D12: Ativo
A14: ALIMENTAÇÃO — HISTÓRICO DE PREÇO DA QUENTINHA
A15: Vigência | C15: Valor unitário (R$) | D15: Observação
A16: De 20/07 a 24/07 | C16: 22 | D16: Valor corrente
A18: COMO USAR
A19: Células amarelas com texto azul são de preenchimento. As demais são fórmulas — não digite por cima.
A20: Nas abas de dia, coluna 'Presença': 1 = diária inteira · 0,5 = meia diária · vazio = não trabalhou.
A21: O valor da quentinha é lançado DENTRO de cada aba de dia — cada data guarda o preço que valeu naquele dia.
A22: A quantidade de quentinhas é livre: pode ser maior que o número de presentes, quando houver unidade adicional.
A23: Outros consumos do dia (gelo, entrega de quentinha) entram como linhas próprias na seção 2 de cada aba de dia.
A24: A aba 'Resumo Semanal' consolida os dias, o gasto por funcionário, as quentinhas por valor unitário e o acumulado da obra.
A25: Aparecem aqui apenas os funcionários que tiveram presença nesta semana.

Sheet Segunda 20-07
A1: SEGUNDA-FEIRA — 20/07/2026
A2: Obra: Selecta – Gil Martins · Av. Gil Martins, 3144 – Três Andares – Teresina/PI · RV Engenharia
A4: 1. MÃO DE OBRA — DETALHAMENTO POR FUNCIONÁRIO
A5: Funcionário | B5: Função | C5: Diária (R$) | D5: Presença | E5: Valor do Dia (R$)
A6: Thiago | B6: Pedreiro | C6: ='Parâmetros'!$C$8 | D6: 1 | E6: =C6*D6
A7: Wiliton | B7: Eletricista | C7: ='Parâmetros'!$C$9 | E7: =C7*D7
A8: Gervasio | B8: Ajudante | C8: ='Parâmetros'!$C$10 | D8: 1 | E8: =C8*D8
A9: Máximo | B9: Ajudante | C9: ='Parâmetros'!$C$11 | E9: =C9*D9
A10: Amigo Máximo | B10: Ajudante | C10: ='Parâmetros'!$C$12 | E10: =C10*D10
A11: SUBTOTAL — MÃO DE OBRA | C11: Diárias: | D11: =SUM(D6:D10) | E11: =SUM(E6:E10)
A13: 2. ALIMENTAÇÃO E OUTROS CONSUMOS DO DIA
A14: Descrição | C14: Valor unitário (R$) | D14: Quantidade | E14: Valor Total (R$)
A15: Quentinhas fornecidas | C15: 22 | D15: 2 | E15: =C15*D15
A17: 3. RESUMO DO DIA — SEGUNDA-FEIRA 20/07
A18: Total de diárias trabalhadas | E18: =D11
A19: Quentinhas fornecidas (un.) | E19: =D15
A20: Custo de mão de obra | E20: =E11
A21: Custo de alimentação | E21: =E15
A22: TOTAL DO DIA | E22: =E20+E21

Sheet Terça 21-07
A1: TERÇA-FEIRA — 21/07/2026
A2: Obra: Selecta – Gil Martins · Av. Gil Martins, 3144 – Três Andares – Teresina/PI · RV Engenharia
A4: 1. MÃO DE OBRA — DETALHAMENTO POR FUNCIONÁRIO
A5: Funcionário | B5: Função | C5: Diária (R$) | D5: Presença | E5: Valor do Dia (R$)
A6: Thiago | B6: Pedreiro | C6: ='Parâmetros'!$C$8 | D6: 1 | E6: =C6*D6
A7: Wiliton | B7: Eletricista | C7: ='Parâmetros'!$C$9 | E7: =C7*D7
A8: Gervasio | B8: Ajudante | C8: ='Parâmetros'!$C$10 | D8: 1 | E8: =C8*D8
A9: Máximo | B9: Ajudante | C9: ='Parâmetros'!$C$11 | E9: =C9*D9
A10: Amigo Máximo | B10: Ajudante | C10: ='Parâmetros'!$C$12 | E10: =C10*D10
A11: SUBTOTAL — MÃO DE OBRA | C11: Diárias: | D11: =SUM(D6:D10) | E11: =SUM(E6:E10)
A13: 2. ALIMENTAÇÃO E OUTROS CONSUMOS DO DIA
A14: Descrição | C14: Valor unitário (R$) | D14: Quantidade | E14: Valor Total (R$)
A15: Quentinhas fornecidas | C15: 22 | D15: 2 | E15: =C15*D15
A17: 3. RESUMO DO DIA — TERÇA-FEIRA 21/07
A18: Total de diárias trabalhadas | E18: =D11
A19: Quentinhas fornecidas (un.) | E19: =D15
A20: Custo de mão de obra | E20: =E11
A21: Custo de alimentação | E21: =E15
A22: TOTAL DO DIA | E22: =E20+E21

Sheet Quarta 22-07
A1: QUARTA-FEIRA — 22/07/2026
A2: Obra: Selecta – Gil Martins · Av. Gil Martins, 3144 – Três Andares – Teresina/PI · RV Engenharia
A4: 1. MÃO DE OBRA — DETALHAMENTO POR FUNCIONÁRIO
A5: Funcionário | B5: Função | C5: Diária (R$) | D5: Presença | E5: Valor do Dia (R$)
A6: Thiago | B6: Pedreiro | C6: ='Parâmetros'!$C$8 | D6: 1 | E6: =C6*D6
A7: Wiliton | B7: Eletricista | C7: ='Parâmetros'!$C$9 | E7: =C7*D7
A8: Gervasio | B8: Ajudante | C8: ='Parâmetros'!$C$10 | D8: 1 | E8: =C8*D8
A9: Máximo | B9: Ajudante | C9: ='Parâmetros'!$C$11 | E9: =C9*D9
A10: Amigo Máximo | B10: Ajudante | C10: ='Parâmetros'!$C$12 | E10: =C10*D10
A11: SUBTOTAL — MÃO DE OBRA | C11: Diárias: | D11: =SUM(D6:D10) | E11: =SUM(E6:E10)
A13: 2. ALIMENTAÇÃO E OUTROS CONSUMOS DO DIA
A14: Descrição | C14: Valor unitário (R$) | D14: Quantidade | E14: Valor Total (R$)
A15: Quentinhas fornecidas | C15: 22 | D15: 2 | E15: =C15*D15
A17: 3. RESUMO DO DIA — QUARTA-FEIRA 22/07
A18: Total de diárias trabalhadas | E18: =D11
A19: Quentinhas fornecidas (un.) | E19: =D15
A20: Custo de mão de obra | E20: =E11
A21: Custo de alimentação | E21: =E15
A22: TOTAL DO DIA | E22: =E20+E21

Sheet Quinta 23-07
A1: QUINTA-FEIRA — 23/07/2026
A2: Obra: Selecta – Gil Martins · Av. Gil Martins, 3144 – Três Andares – Teresina/PI · RV Engenharia
A4: 1. MÃO DE OBRA — DETALHAMENTO POR FUNCIONÁRIO
A5: Funcionário | B5: Função | C5: Diária (R$) | D5: Presença | E5: Valor do Dia (R$)
A6: Thiago | B6: Pedreiro | C6: ='Parâmetros'!$C$8 | D6: 1 | E6: =C6*D6
A7: Wiliton | B7: Eletricista | C7: ='Parâmetros'!$C$9 | D7: 1 | E7: =C7*D7
A8: Gervasio | B8: Ajudante | C8: ='Parâmetros'!$C$10 | D8: 1 | E8: =C8*D8
A9: Máximo | B9: Ajudante | C9: ='Parâmetros'!$C$11 | E9: =C9*D9
A10: Amigo Máximo | B10: Ajudante | C10: ='Parâmetros'!$C$12 | E10: =C10*D10
A11: SUBTOTAL — MÃO DE OBRA | C11: Diárias: | D11: =SUM(D6:D10) | E11: =SUM(E6:E10)
A13: 2. ALIMENTAÇÃO E OUTROS CONSUMOS DO DIA
A14: Descrição | C14: Valor unitário (R$) | D14: Quantidade | E14: Valor Total (R$)
A15: Quentinhas fornecidas | C15: 22 | D15: 3 | E15: =C15*D15
A17: 3. RESUMO DO DIA — QUINTA-FEIRA 23/07
A18: Total de diárias trabalhadas | E18: =D11
A19: Quentinhas fornecidas (un.) | E19: =D15
A20: Custo de mão de obra | E20: =E11
A21: Custo de alimentação | E21: =E15
A22: TOTAL DO DIA | E22: =E20+E21
A24: Observação: Entrada de Wiliton (eletricista, R$ 200,00)

Sheet Sexta 24-07
A1: SEXTA-FEIRA — 24/07/2026
A2: Obra: Selecta – Gil Martins · Av. Gil Martins, 3144 – Três Andares – Teresina/PI · RV Engenharia
A4: 1. MÃO DE OBRA — DETALHAMENTO POR FUNCIONÁRIO
A5: Funcionário | B5: Função | C5: Diária (R$) | D5: Presença | E5: Valor do Dia (R$)
A6: Thiago | B6: Pedreiro | C6: ='Parâmetros'!$C$8 | D6: 1 | E6: =C6*D6
A7: Wiliton | B7: Eletricista | C7: ='Parâmetros'!$C$9 | D7: 1 | E7: =C7*D7
A8: Gervasio | B8: Ajudante | C8: ='Parâmetros'!$C$10 | D8: 1 | E8: =C8*D8
A9: Máximo | B9: Ajudante | C9: ='Parâmetros'!$C$11 | E9: =C9*D9
A10: Amigo Máximo | B10: Ajudante | C10: ='Parâmetros'!$C$12 | E10: =C10*D10
A11: SUBTOTAL — MÃO DE OBRA | C11: Diárias: | D11: =SUM(D6:D10) | E11: =SUM(E6:E10)
A13: 2. ALIMENTAÇÃO E OUTROS CONSUMOS DO DIA
A14: Descrição | C14: Valor unitário (R$) | D14: Quantidade | E14: Valor Total (R$)
A15: Quentinhas fornecidas | C15: 22 | D15: 3 | E15: =C15*D15
A17: 3. RESUMO DO DIA — SEXTA-FEIRA 24/07
A18: Total de diárias trabalhadas | E18: =D11
A19: Quentinhas fornecidas (un.) | E19: =D15
A20: Custo de mão de obra | E20: =E11
A21: Custo de alimentação | E21: =E15
A22: TOTAL DO DIA | E22: =E20+E21

Sheet Sábado 25-07
A1: SÁBADO — 25/07/2026
A2: Obra: Selecta – Gil Martins · Av. Gil Martins, 3144 – Três Andares – Teresina/PI · RV Engenharia
A4: 1. MÃO DE OBRA — DETALHAMENTO POR FUNCIONÁRIO
A5: Funcionário | B5: Função | C5: Diária (R$) | D5: Presença | E5: Valor do Dia (R$)
A6: Thiago | B6: Pedreiro | C6: ='Parâmetros'!$C$8 | D6: 1 | E6: =C6*D6
A7: Wiliton | B7: Eletricista | C7: ='Parâmetros'!$C$9 | E7: =C7*D7
A8: Gervasio | B8: Ajudante | C8: ='Parâmetros'!$C$10 | D8: 1 | E8: =C8*D8
A9: Máximo | B9: Ajudante | C9: ='Parâmetros'!$C$11 | D9: 1 | E9: =C9*D9
A10: Amigo Máximo | B10: Ajudante | C10: ='Parâmetros'!$C$12 | D10: 1 | E10: =C10*D10
A11: SUBTOTAL — MÃO DE OBRA | C11: Diárias: | D11: =SUM(D6:D10) | E11: =SUM(E6:E10)
A13: 2. ALIMENTAÇÃO E OUTROS CONSUMOS DO DIA
A14: Descrição | C14: Valor unitário (R$) | D14: Quantidade | E14: Valor Total (R$)
A15: Quentinhas fornecidas | C15: 22 | D15: 0 | E15: =C15*D15
A17: 3. RESUMO DO DIA — SÁBADO 25/07
A18: Total de diárias trabalhadas | E18: =D11
A19: Quentinhas fornecidas (un.) | E19: =D15
A20: Custo de mão de obra | E20: =E11
A21: Custo de alimentação | E21: =E15
A22: TOTAL DO DIA | E22: =E20+E21
A24: Observação: Sábado até meio-dia: diária integral e sem quentinha. Entrada de Máximo e Amigo Máximo (ajudantes, R$ 100,00)

Sheet Resumo Semanal
A1: RESUMO GERAL DA SEMANA — 20/07 A 25/07/2026
A2: Obra: Selecta – Gil Martins · Av. Gil Martins, 3144 – Três Andares – Teresina/PI · RV Engenharia
A4: 1. FECHAMENTO POR DIA
A5: Dia | B5: Data | C5: Diárias | D5: Mão de Obra (R$) | E5: Quentinhas (un.) | F5: Alim. e outros (R$) | G5: Total do Dia (R$)
A6: Segunda | B6: 46223 | C6: ='Segunda 20-07'!$E$18 | D6: ='Segunda 20-07'!$E$20 | E6: ='Segunda 20-07'!$E$19 | F6: ='Segunda 20-07'!$E$21 | G6: ='Segunda 20-07'!$E$22
A7: Terça | B7: 46224 | C7: ='Terça 21-07'!$E$18 | D7: ='Terça 21-07'!$E$20 | E7: ='Terça 21-07'!$E$19 | F7: ='Terça 21-07'!$E$21 | G7: ='Terça 21-07'!$E$22
A8: Quarta | B8: 46225 | C8: ='Quarta 22-07'!$E$18 | D8: ='Quarta 22-07'!$E$20 | E8: ='Quarta 22-07'!$E$19 | F8: ='Quarta 22-07'!$E$21 | G8: ='Quarta 22-07'!$E$22
A9: Quinta | B9: 46226 | C9: ='Quinta 23-07'!$E$18 | D9: ='Quinta 23-07'!$E$20 | E9: ='Quinta 23-07'!$E$19 | F9: ='Quinta 23-07'!$E$21 | G9: ='Quinta 23-07'!$E$22
A10: Sexta | B10: 46227 | C10: ='Sexta 24-07'!$E$18 | D10: ='Sexta 24-07'!$E$20 | E10: ='Sexta 24-07'!$E$19 | F10: ='Sexta 24-07'!$E$21 | G10: ='Sexta 24-07'!$E$22
A11: Sábado | B11: 46228 | C11: ='Sábado 25-07'!$E$18 | D11: ='Sábado 25-07'!$E$20 | E11: ='Sábado 25-07'!$E$19 | F11: ='Sábado 25-07'!$E$21 | G11: ='Sábado 25-07'!$E$22
A12: TOTAL DA SEMANA | C12: =SUM(C6:C11) | D12: =SUM(D6:D11) | E12: =SUM(E6:E11) | F12: =SUM(F6:F11) | G12: =SUM(G6:G11)
A14: 2. GASTOS POR FUNCIONÁRIO
A15: Funcionário | B15: Função | C15: Diária (R$) | D15: Diárias na Semana | G15: Total a Pagar (R$)
A16: Thiago | B16: Pedreiro | C16: ='Parâmetros'!$C$8 | D16: ='Segunda 20-07'!$D$6+'Terça 21-07'!$D$6+'Quarta 22-07'!$D$6+'Quinta 23-07'!$D$6+'Sexta 24-07'!$D$6+'Sábado 25-07'!$D$6 | G16: =C16*D16
A17: Wiliton | B17: Eletricista | C17: ='Parâmetros'!$C$9 | D17: ='Segunda 20-07'!$D$7+'Terça 21-07'!$D$7+'Quarta 22-07'!$D$7+'Quinta 23-07'!$D$7+'Sexta 24-07'!$D$7+'Sábado 25-07'!$D$7 | G17: =C17*D17
A18: Gervasio | B18: Ajudante | C18: ='Parâmetros'!$C$10 | D18: ='Segunda 20-07'!$D$8+'Terça 21-07'!$D$8+'Quarta 22-07'!$D$8+'Quinta 23-07'!$D$8+'Sexta 24-07'!$D$8+'Sábado 25-07'!$D$8 | G18: =C18*D18
A19: Máximo | B19: Ajudante | C19: ='Parâmetros'!$C$11 | D19: ='Segunda 20-07'!$D$9+'Terça 21-07'!$D$9+'Quarta 22-07'!$D$9+'Quinta 23-07'!$D$9+'Sexta 24-07'!$D$9+'Sábado 25-07'!$D$9 | G19: =C19*D19
A20: Amigo Máximo | B20: Ajudante | C20: ='Parâmetros'!$C$12 | D20: ='Segunda 20-07'!$D$10+'Terça 21-07'!$D$10+'Quarta 22-07'!$D$10+'Quinta 23-07'!$D$10+'Sexta 24-07'!$D$10+'Sábado 25-07'!$D$10 | G20: =C20*D20
A21: TOTAL — MÃO DE OBRA DA SEMANA | D21: =SUM(D16:D20) | G21: =SUM(G16:G20)
A23: 3. GASTOS COM QUENTINHAS — SEPARADO POR VALOR UNITÁRIO (E OUTROS CONSUMOS)
A24: Valor unitário / item | B24: Dias em que foi usado | E24: Quantidade (un.) | G24: Custo (R$)
A25: 22 | B25: 20/07, 21/07, 22/07, 23/07, 24/07 | E25: ='Segunda 20-07'!$D$15+'Terça 21-07'!$D$15+'Quarta 22-07'!$D$15+'Quinta 23-07'!$D$15+'Sexta 24-07'!$D$15 | G25: ='Segunda 20-07'!$E$15+'Terça 21-07'!$E$15+'Quarta 22-07'!$E$15+'Quinta 23-07'!$E$15+'Sexta 24-07'!$E$15
A26: TOTAL DE QUENTINHAS DA SEMANA | E26: =SUM(E25:E25) | G26: =SUM(G25:G25)
A28: 4. GASTO GERAL DA SEMANA
A29: Total de mão de obra | G29: =G21
A30: Total de alimentação e outros | G30: =G26
A31: GASTO GERAL DA SEMANA | G31: =G29+G30
A33: 5. ACUMULADO DA OBRA
A34: Período | C34: Diárias | D34: Mão de Obra (R$) | E34: Quentinhas (un.) | F34: Alim. e outros (R$) | G34: Total (R$)
A35: Semana 1 — 20/07 a 25/07 | C35: =C12 | D35: =D12 | E35: =E12 | F35: =F12 | G35: =G12
A36: TOTAL ACUMULADO DA OBRA | C36: =SUM(C35:C35) | D36: =SUM(D35:D35) | E36: =SUM(E35:E35) | F36: =SUM(F35:F35) | G36: =SUM(G35:G35)
A38: Notas da semana: 23/07 — Entrada de Wiliton (eletricista, R$ 200,00); 25/07 — Sábado até meio-dia: diária integral e sem quentinha. Entrada de Máximo e Amigo Máximo (ajudantes, R$ 100,00). Constam apenas os funcionários com presença na semana. Os totais de mão de obra dos blocos 1 e 2 devem ser idênticos.
