Workbook

Sheet Parâmetros
A1: RV ENGENHARIA — CONTROLE DE DIÁRIAS E CUSTOS
A2: Obra: Selecta – Gil Martins · Av. Gil Martins, 3144 – Três Andares – Teresina/PI · RV Engenharia
A4: Semana de referência | C4: 46244 | D4: a | E4: 46248
A6: EQUIPE E VALORES DE DIÁRIA
A7: Funcionário | B7: Função | C7: Diária (R$) | D7: Situação
A8: Thiago | B8: Pedreiro | C8: 200 | D8: Ativo
A9: Wiliton | B9: Eletricista | C9: 200 | D9: Ativo
A10: Rafael | B10: Eletricista | C10: 200 | D10: Ativo
A11: Iago | B11: Servente | C11: 90 | D11: Ativo
A13: ALIMENTAÇÃO — HISTÓRICO DE PREÇO DA QUENTINHA
A14: Vigência | C14: Valor unitário (R$) | D14: Observação
A15: De 20/07 a 28/07 | C15: 22
A16: De 29/07 a 03/08 | C16: 15
A17: Dia 04/08 | C17: 22
A18: Dia 05/08 | C18: 15
A19: De 06/08 a 13/08 | C19: 18
A20: Dia 14/08 | C20: 22 | D20: Valor corrente
A22: COMO USAR
A23: Células amarelas com texto azul são de preenchimento. As demais são fórmulas — não digite por cima.
A24: Nas abas de dia, coluna 'Presença': 1 = diária inteira · 0,5 = meia diária · vazio = não trabalhou.
A25: O valor da quentinha é lançado DENTRO de cada aba de dia — cada data guarda o preço que valeu naquele dia.
A26: A quantidade de quentinhas é livre: pode ser maior que o número de presentes, quando houver unidade adicional.
A27: Outros consumos do dia (gelo, entrega de quentinha) entram como linhas próprias na seção 2 de cada aba de dia.
A28: A aba 'Resumo Semanal' consolida os dias, o gasto por funcionário, as quentinhas por valor unitário e o acumulado da obra.
A29: Aparecem aqui apenas os funcionários que tiveram presença nesta semana.

Sheet Segunda 10-08
A1: SEGUNDA-FEIRA — 10/08/2026
A2: Obra: Selecta – Gil Martins · Av. Gil Martins, 3144 – Três Andares – Teresina/PI · RV Engenharia
A4: 1. MÃO DE OBRA — DETALHAMENTO POR FUNCIONÁRIO
A5: Funcionário | B5: Função | C5: Diária (R$) | D5: Presença | E5: Valor do Dia (R$)
A6: Thiago | B6: Pedreiro | C6: ='Parâmetros'!$C$8 | D6: 1 | E6: =C6*D6
A7: Wiliton | B7: Eletricista | C7: ='Parâmetros'!$C$9 | D7: 1 | E7: =C7*D7
A8: Rafael | B8: Eletricista | C8: ='Parâmetros'!$C$10 | E8: =C8*D8
A9: Iago | B9: Servente | C9: ='Parâmetros'!$C$11 | E9: =C9*D9
A10: SUBTOTAL — MÃO DE OBRA | C10: Diárias: | D10: =SUM(D6:D9) | E10: =SUM(E6:E9)
A12: 2. ALIMENTAÇÃO E OUTROS CONSUMOS DO DIA
A13: Descrição | C13: Valor unitário (R$) | D13: Quantidade | E13: Valor Total (R$)
A14: Quentinhas fornecidas | C14: 18 | D14: 2 | E14: =C14*D14
A16: 3. RESUMO DO DIA — SEGUNDA-FEIRA 10/08
A17: Total de diárias trabalhadas | E17: =D10
A18: Quentinhas fornecidas (un.) | E18: =D14
A19: Custo de mão de obra | E19: =E10
A20: Custo de alimentação | E20: =E14
A21: TOTAL DO DIA | E21: =E19+E20

Sheet Terça 11-08
A1: TERÇA-FEIRA — 11/08/2026
A2: Obra: Selecta – Gil Martins · Av. Gil Martins, 3144 – Três Andares – Teresina/PI · RV Engenharia
A4: 1. MÃO DE OBRA — DETALHAMENTO POR FUNCIONÁRIO
A5: Funcionário | B5: Função | C5: Diária (R$) | D5: Presença | E5: Valor do Dia (R$)
A6: Thiago | B6: Pedreiro | C6: ='Parâmetros'!$C$8 | D6: 1 | E6: =C6*D6
A7: Wiliton | B7: Eletricista | C7: ='Parâmetros'!$C$9 | D7: 1 | E7: =C7*D7
A8: Rafael | B8: Eletricista | C8: ='Parâmetros'!$C$10 | D8: 1 | E8: =C8*D8
A9: Iago | B9: Servente | C9: ='Parâmetros'!$C$11 | E9: =C9*D9
A10: SUBTOTAL — MÃO DE OBRA | C10: Diárias: | D10: =SUM(D6:D9) | E10: =SUM(E6:E9)
A12: 2. ALIMENTAÇÃO E OUTROS CONSUMOS DO DIA
A13: Descrição | C13: Valor unitário (R$) | D13: Quantidade | E13: Valor Total (R$)
A14: Quentinhas fornecidas | C14: 18 | D14: 4 | E14: =C14*D14
A16: 3. RESUMO DO DIA — TERÇA-FEIRA 11/08
A17: Total de diárias trabalhadas | E17: =D10
A18: Quentinhas fornecidas (un.) | E18: =D14
A19: Custo de mão de obra | E19: =E10
A20: Custo de alimentação | E20: =E14
A21: TOTAL DO DIA | E21: =E19+E20
A23: Observação: Rafael (eletricista, R$ 200,00) entra como reforço. 4 quentinhas para 3 funcionários: 1 unidade para o responsável pela obra

Sheet Quarta 12-08
A1: QUARTA-FEIRA — 12/08/2026
A2: Obra: Selecta – Gil Martins · Av. Gil Martins, 3144 – Três Andares – Teresina/PI · RV Engenharia
A4: 1. MÃO DE OBRA — DETALHAMENTO POR FUNCIONÁRIO
A5: Funcionário | B5: Função | C5: Diária (R$) | D5: Presença | E5: Valor do Dia (R$)
A6: Thiago | B6: Pedreiro | C6: ='Parâmetros'!$C$8 | D6: 1 | E6: =C6*D6
A7: Wiliton | B7: Eletricista | C7: ='Parâmetros'!$C$9 | E7: =C7*D7
A8: Rafael | B8: Eletricista | C8: ='Parâmetros'!$C$10 | E8: =C8*D8
A9: Iago | B9: Servente | C9: ='Parâmetros'!$C$11 | D9: 0.5 | E9: =C9*D9
A10: SUBTOTAL — MÃO DE OBRA | C10: Diárias: | D10: =SUM(D6:D9) | E10: =SUM(E6:E9)
A12: 2. ALIMENTAÇÃO E OUTROS CONSUMOS DO DIA
A13: Descrição | C13: Valor unitário (R$) | D13: Quantidade | E13: Valor Total (R$)
A14: Quentinhas fornecidas | C14: 18 | D14: 2 | E14: =C14*D14
A16: 3. RESUMO DO DIA — QUARTA-FEIRA 12/08
A17: Total de diárias trabalhadas | E17: =D10
A18: Quentinhas fornecidas (un.) | E18: =D14
A19: Custo de mão de obra | E19: =E10
A20: Custo de alimentação | E20: =E14
A21: TOTAL DO DIA | E21: =E19+E20
A23: Observação: Integração de Iago (servente, R$ 90,00) com meio expediente no primeiro dia (meia diária)

Sheet Quinta 13-08
A1: QUINTA-FEIRA — 13/08/2026
A2: Obra: Selecta – Gil Martins · Av. Gil Martins, 3144 – Três Andares – Teresina/PI · RV Engenharia
A4: 1. MÃO DE OBRA — DETALHAMENTO POR FUNCIONÁRIO
A5: Funcionário | B5: Função | C5: Diária (R$) | D5: Presença | E5: Valor do Dia (R$)
A6: Thiago | B6: Pedreiro | C6: ='Parâmetros'!$C$8 | D6: 1 | E6: =C6*D6
A7: Wiliton | B7: Eletricista | C7: ='Parâmetros'!$C$9 | E7: =C7*D7
A8: Rafael | B8: Eletricista | C8: ='Parâmetros'!$C$10 | E8: =C8*D8
A9: Iago | B9: Servente | C9: ='Parâmetros'!$C$11 | D9: 1 | E9: =C9*D9
A10: SUBTOTAL — MÃO DE OBRA | C10: Diárias: | D10: =SUM(D6:D9) | E10: =SUM(E6:E9)
A12: 2. ALIMENTAÇÃO E OUTROS CONSUMOS DO DIA
A13: Descrição | C13: Valor unitário (R$) | D13: Quantidade | E13: Valor Total (R$)
A14: Quentinhas fornecidas | C14: 18 | D14: 2 | E14: =C14*D14
A16: 3. RESUMO DO DIA — QUINTA-FEIRA 13/08
A17: Total de diárias trabalhadas | E17: =D10
A18: Quentinhas fornecidas (un.) | E18: =D14
A19: Custo de mão de obra | E19: =E10
A20: Custo de alimentação | E20: =E14
A21: TOTAL DO DIA | E21: =E19+E20
A23: Observação: Iago em expediente integral

Sheet Sexta 14-08
A1: SEXTA-FEIRA — 14/08/2026
A2: Obra: Selecta – Gil Martins · Av. Gil Martins, 3144 – Três Andares – Teresina/PI · RV Engenharia
A4: 1. MÃO DE OBRA — DETALHAMENTO POR FUNCIONÁRIO
A5: Funcionário | B5: Função | C5: Diária (R$) | D5: Presença | E5: Valor do Dia (R$)
A6: Thiago | B6: Pedreiro | C6: ='Parâmetros'!$C$8 | D6: 1 | E6: =C6*D6
A7: Wiliton | B7: Eletricista | C7: ='Parâmetros'!$C$9 | D7: 1 | E7: =C7*D7
A8: Rafael | B8: Eletricista | C8: ='Parâmetros'!$C$10 | E8: =C8*D8
A9: Iago | B9: Servente | C9: ='Parâmetros'!$C$11 | D9: 1 | E9: =C9*D9
A10: SUBTOTAL — MÃO DE OBRA | C10: Diárias: | D10: =SUM(D6:D9) | E10: =SUM(E6:E9)
A12: 2. ALIMENTAÇÃO E OUTROS CONSUMOS DO DIA
A13: Descrição | C13: Valor unitário (R$) | D13: Quantidade | E13: Valor Total (R$)
A14: Quentinhas fornecidas | C14: 22 | D14: 3 | E14: =C14*D14
A16: 3. RESUMO DO DIA — SEXTA-FEIRA 14/08
A17: Total de diárias trabalhadas | E17: =D10
A18: Quentinhas fornecidas (un.) | E18: =D14
A19: Custo de mão de obra | E19: =E10
A20: Custo de alimentação | E20: =E14
A21: TOTAL DO DIA | E21: =E19+E20
A23: Observação: Quentinha a R$ 22,00 (fornecedor de R$ 18,00 indisponível). Encerramento da semana na sexta-feira

Sheet Resumo Semanal
A1: RESUMO GERAL DA SEMANA — 10/08 A 14/08/2026
A2: Obra: Selecta – Gil Martins · Av. Gil Martins, 3144 – Três Andares – Teresina/PI · RV Engenharia
A4: 1. FECHAMENTO POR DIA
A5: Dia | B5: Data | C5: Diárias | D5: Mão de Obra (R$) | E5: Quentinhas (un.) | F5: Alim. e outros (R$) | G5: Total do Dia (R$)
A6: Segunda | B6: 46244 | C6: ='Segunda 10-08'!$E$17 | D6: ='Segunda 10-08'!$E$19 | E6: ='Segunda 10-08'!$E$18 | F6: ='Segunda 10-08'!$E$20 | G6: ='Segunda 10-08'!$E$21
A7: Terça | B7: 46245 | C7: ='Terça 11-08'!$E$17 | D7: ='Terça 11-08'!$E$19 | E7: ='Terça 11-08'!$E$18 | F7: ='Terça 11-08'!$E$20 | G7: ='Terça 11-08'!$E$21
A8: Quarta | B8: 46246 | C8: ='Quarta 12-08'!$E$17 | D8: ='Quarta 12-08'!$E$19 | E8: ='Quarta 12-08'!$E$18 | F8: ='Quarta 12-08'!$E$20 | G8: ='Quarta 12-08'!$E$21
A9: Quinta | B9: 46247 | C9: ='Quinta 13-08'!$E$17 | D9: ='Quinta 13-08'!$E$19 | E9: ='Quinta 13-08'!$E$18 | F9: ='Quinta 13-08'!$E$20 | G9: ='Quinta 13-08'!$E$21
A10: Sexta | B10: 46248 | C10: ='Sexta 14-08'!$E$17 | D10: ='Sexta 14-08'!$E$19 | E10: ='Sexta 14-08'!$E$18 | F10: ='Sexta 14-08'!$E$20 | G10: ='Sexta 14-08'!$E$21
A11: TOTAL DA SEMANA | C11: =SUM(C6:C10) | D11: =SUM(D6:D10) | E11: =SUM(E6:E10) | F11: =SUM(F6:F10) | G11: =SUM(G6:G10)
A13: 2. GASTOS POR FUNCIONÁRIO
A14: Funcionário | B14: Função | C14: Diária (R$) | D14: Diárias na Semana | G14: Total a Pagar (R$)
A15: Thiago | B15: Pedreiro | C15: ='Parâmetros'!$C$8 | D15: ='Segunda 10-08'!$D$6+'Terça 11-08'!$D$6+'Quarta 12-08'!$D$6+'Quinta 13-08'!$D$6+'Sexta 14-08'!$D$6 | G15: =C15*D15
A16: Wiliton | B16: Eletricista | C16: ='Parâmetros'!$C$9 | D16: ='Segunda 10-08'!$D$7+'Terça 11-08'!$D$7+'Quarta 12-08'!$D$7+'Quinta 13-08'!$D$7+'Sexta 14-08'!$D$7 | G16: =C16*D16
A17: Rafael | B17: Eletricista | C17: ='Parâmetros'!$C$10 | D17: ='Segunda 10-08'!$D$8+'Terça 11-08'!$D$8+'Quarta 12-08'!$D$8+'Quinta 13-08'!$D$8+'Sexta 14-08'!$D$8 | G17: =C17*D17
A18: Iago | B18: Servente | C18: ='Parâmetros'!$C$11 | D18: ='Segunda 10-08'!$D$9+'Terça 11-08'!$D$9+'Quarta 12-08'!$D$9+'Quinta 13-08'!$D$9+'Sexta 14-08'!$D$9 | G18: =C18*D18
A19: TOTAL — MÃO DE OBRA DA SEMANA | D19: =SUM(D15:D18) | G19: =SUM(G15:G18)
A21: 3. GASTOS COM QUENTINHAS — SEPARADO POR VALOR UNITÁRIO (E OUTROS CONSUMOS)
A22: Valor unitário / item | B22: Dias em que foi usado | E22: Quantidade (un.) | G22: Custo (R$)
A23: 18 | B23: 10/08, 11/08, 12/08, 13/08 | E23: ='Segunda 10-08'!$D$14+'Terça 11-08'!$D$14+'Quarta 12-08'!$D$14+'Quinta 13-08'!$D$14 | G23: ='Segunda 10-08'!$E$14+'Terça 11-08'!$E$14+'Quarta 12-08'!$E$14+'Quinta 13-08'!$E$14
A24: 22 | B24: 14/08 | E24: ='Sexta 14-08'!$D$14 | G24: ='Sexta 14-08'!$E$14
A25: TOTAL DE QUENTINHAS DA SEMANA | E25: =SUM(E23:E24) | G25: =SUM(G23:G24)
A27: 4. GASTO GERAL DA SEMANA
A28: Total de mão de obra | G28: =G19
A29: Total de alimentação e outros | G29: =G25
A30: GASTO GERAL DA SEMANA | G30: =G28+G29
A32: 5. ACUMULADO DA OBRA
A33: Período | C33: Diárias | D33: Mão de Obra (R$) | E33: Quentinhas (un.) | F33: Alim. e outros (R$) | G33: Total (R$)
A34: Semana 1 — 20/07 a 25/07 | C34: 16 | D34: 2340 | E34: 12 | F34: 264 | G34: 2604
A35: Semana 2 — 27/07 a 31/07 | C35: 19 | D35: 2370 | E35: 19 | F35: 334 | G35: 2704
A36: Semana 3 — 03/08 a 07/08 | C36: 14 | D36: 2360 | E36: 14 | F36: 246 | G36: 2606
A37: Semana 4 — 10/08 a 14/08 | C37: =C11 | D37: =D11 | E37: =E11 | F37: =F11 | G37: =G11
A38: TOTAL ACUMULADO DA OBRA | C38: =SUM(C34:C37) | D38: =SUM(D34:D37) | E38: =SUM(E34:E37) | F38: =SUM(F34:F37) | G38: =SUM(G34:G37)
A40: Notas da semana: 11/08 — Rafael (eletricista, R$ 200,00) entra como reforço. 4 quentinhas para 3 funcionários: 1 unidade para o responsável pela obra; 12/08 — Integração de Iago (servente, R$ 90,00) com meio expediente no primeiro dia (meia diária); 13/08 — Iago em expediente integral; 14/08 — Quentinha a R$ 22,00 (fornecedor de R$ 18,00 indisponível). Encerramento da semana na sexta-feira. Constam apenas os funcionários com presença na semana. Os totais de mão de obra dos blocos 1 e 2 devem ser idênticos.
