Workbook

Sheet Parâmetros
A1: RV ENGENHARIA — CONTROLE DE DIÁRIAS E CUSTOS
A2: Obra: Selecta – Gil Martins · Av. Gil Martins, 3144 – Três Andares – Teresina/PI · RV Engenharia
A4: Semana de referência | C4: 46272 | D4: a | E4: 46276
A6: EQUIPE E VALORES DE DIÁRIA
A7: Funcionário | B7: Função | C7: Diária (R$) | D7: Situação
A8: Thiago | B8: Pedreiro | C8: 200 | D8: Ativo
A9: Francisco | B9: Pedreiro | C9: 160 | D9: Ativo
A10: Rufino | B10: Servente | C10: 100 | D10: Ativo
A11: Carlos | B11: Servente | C11: 100 | D11: Ativo
A13: ALIMENTAÇÃO — HISTÓRICO DE PREÇO DA QUENTINHA
A14: Vigência | C14: Valor unitário (R$) | D14: Observação
A15: De 20/07 a 28/07 | C15: 22
A16: De 29/07 a 03/08 | C16: 15
A17: Dia 04/08 | C17: 22
A18: Dia 05/08 | C18: 15
A19: De 06/08 a 13/08 | C19: 18
A20: Dia 14/08 | C20: 22
A21: De 17/08 a 25/08 | C21: 18
A22: De 26/08 a 31/08 | C22: 22
A23: De 01/09 a 11/09 | C23: 18 | D23: Valor corrente
A25: COMO USAR
A26: Células amarelas com texto azul são de preenchimento. As demais são fórmulas — não digite por cima.
A27: Nas abas de dia, coluna 'Presença': 1 = diária inteira · 0,5 = meia diária · vazio = não trabalhou.
A28: O valor da quentinha é lançado DENTRO de cada aba de dia — cada data guarda o preço que valeu naquele dia.
A29: A quantidade de quentinhas é livre: pode ser maior que o número de presentes, quando houver unidade adicional.
A30: Outros consumos do dia (gelo, entrega de quentinha) entram como linhas próprias na seção 2 de cada aba de dia.
A31: A aba 'Resumo Semanal' consolida os dias, o gasto por funcionário, as quentinhas por valor unitário e o acumulado da obra.
A32: Aparecem aqui apenas os funcionários que tiveram presença nesta semana.

Sheet Segunda 07-09
A1: SEGUNDA-FEIRA — 07/09/2026
A2: Obra: Selecta – Gil Martins · Av. Gil Martins, 3144 – Três Andares – Teresina/PI · RV Engenharia
A4: 1. MÃO DE OBRA — DETALHAMENTO POR FUNCIONÁRIO
A5: Funcionário | B5: Função | C5: Diária (R$) | D5: Presença | E5: Valor do Dia (R$)
A6: Thiago | B6: Pedreiro | C6: =Parâmetros!$C$8 -> 200 | D6: 1 | E6: =C6*D6 -> 200
A7: Francisco | B7: Pedreiro | C7: =Parâmetros!$C$9 -> 160 | E7: =C7*D7 -> 0
A8: Rufino | B8: Servente | C8: =Parâmetros!$C$10 -> 100 | E8: =C8*D8 -> 0
A9: Carlos | B9: Servente | C9: =Parâmetros!$C$11 -> 100 | E9: =C9*D9 -> 0
A10: SUBTOTAL — MÃO DE OBRA | C10: Diárias: | D10: =SUM(D6:D9) -> 1 | E10: =SUM(E6:E9) -> 200
A12: 2. ALIMENTAÇÃO E OUTROS CONSUMOS DO DIA
A13: Descrição | C13: Valor unitário (R$) | D13: Quantidade | E13: Valor Total (R$)
A14: Quentinhas fornecidas | C14: 18 | D14: 0 | E14: =C14*D14 -> 0
A16: 3. RESUMO DO DIA — SEGUNDA-FEIRA 07/09
A17: Total de diárias trabalhadas | E17: =D10 -> 1
A18: Quentinhas fornecidas (un.) | E18: =D14 -> 0
A19: Custo de mão de obra | E19: =E10 -> 200
A20: Custo de alimentação | E20: =E14 -> 0
A21: TOTAL DO DIA | E21: =E19+E20 -> 200
A23: Observação: Feriado (Independência): expediente até meio-dia, diária integral e sem quentinha

Sheet Terça 08-09
A1: TERÇA-FEIRA — 08/09/2026
A2: Obra: Selecta – Gil Martins · Av. Gil Martins, 3144 – Três Andares – Teresina/PI · RV Engenharia
A4: 1. MÃO DE OBRA — DETALHAMENTO POR FUNCIONÁRIO
A5: Funcionário | B5: Função | C5: Diária (R$) | D5: Presença | E5: Valor do Dia (R$)
A6: Thiago | B6: Pedreiro | C6: =Parâmetros!$C$8 -> 200 | D6: 1 | E6: =C6*D6 -> 200
A7: Francisco | B7: Pedreiro | C7: =Parâmetros!$C$9 -> 160 | D7: 1 | E7: =C7*D7 -> 160
A8: Rufino | B8: Servente | C8: =Parâmetros!$C$10 -> 100 | D8: 1 | E8: =C8*D8 -> 100
A9: Carlos | B9: Servente | C9: =Parâmetros!$C$11 -> 100 | D9: 1 | E9: =C9*D9 -> 100
A10: SUBTOTAL — MÃO DE OBRA | C10: Diárias: | D10: =SUM(D6:D9) -> 4 | E10: =SUM(E6:E9) -> 560
A12: 2. ALIMENTAÇÃO E OUTROS CONSUMOS DO DIA
A13: Descrição | C13: Valor unitário (R$) | D13: Quantidade | E13: Valor Total (R$)
A14: Quentinhas fornecidas | C14: 18 | D14: 4 | E14: =C14*D14 -> 72
A15: Gelo | C15: 6 | D15: 2 | E15: =C15*D15 -> 12
A16: SUBTOTAL — ALIMENTAÇÃO E OUTROS | E16: =SUM(E14:E15) -> 84
A18: 3. RESUMO DO DIA — TERÇA-FEIRA 08/09
A19: Total de diárias trabalhadas | E19: =D10 -> 4
A20: Quentinhas fornecidas (un.) | E20: =D14 -> 4
A21: Custo de mão de obra | E21: =E10 -> 560
A22: Custo de alimentação e outros | E22: =E16 -> 84
A23: TOTAL DO DIA | E23: =E21+E22 -> 644
A25: Observação: Entrada de Francisco (pedreiro, R$ 160,00), Rufino e Carlos (serventes, R$ 100,00). Início da compra de gelo

Sheet Quarta 09-09
A1: QUARTA-FEIRA — 09/09/2026
A2: Obra: Selecta – Gil Martins · Av. Gil Martins, 3144 – Três Andares – Teresina/PI · RV Engenharia
A4: 1. MÃO DE OBRA — DETALHAMENTO POR FUNCIONÁRIO
A5: Funcionário | B5: Função | C5: Diária (R$) | D5: Presença | E5: Valor do Dia (R$)
A6: Thiago | B6: Pedreiro | C6: =Parâmetros!$C$8 -> 200 | D6: 1 | E6: =C6*D6 -> 200
A7: Francisco | B7: Pedreiro | C7: =Parâmetros!$C$9 -> 160 | D7: 1 | E7: =C7*D7 -> 160
A8: Rufino | B8: Servente | C8: =Parâmetros!$C$10 -> 100 | D8: 1 | E8: =C8*D8 -> 100
A9: Carlos | B9: Servente | C9: =Parâmetros!$C$11 -> 100 | D9: 1 | E9: =C9*D9 -> 100
A10: SUBTOTAL — MÃO DE OBRA | C10: Diárias: | D10: =SUM(D6:D9) -> 4 | E10: =SUM(E6:E9) -> 560
A12: 2. ALIMENTAÇÃO E OUTROS CONSUMOS DO DIA
A13: Descrição | C13: Valor unitário (R$) | D13: Quantidade | E13: Valor Total (R$)
A14: Quentinhas fornecidas | C14: 18 | D14: 4 | E14: =C14*D14 -> 72
A15: Gelo | C15: 6 | D15: 2 | E15: =C15*D15 -> 12
A16: SUBTOTAL — ALIMENTAÇÃO E OUTROS | E16: =SUM(E14:E15) -> 84
A18: 3. RESUMO DO DIA — QUARTA-FEIRA 09/09
A19: Total de diárias trabalhadas | E19: =D10 -> 4
A20: Quentinhas fornecidas (un.) | E20: =D14 -> 4
A21: Custo de mão de obra | E21: =E10 -> 560
A22: Custo de alimentação e outros | E22: =E16 -> 84
A23: TOTAL DO DIA | E23: =E21+E22 -> 644

Sheet Quinta 10-09
A1: QUINTA-FEIRA — 10/09/2026
A2: Obra: Selecta – Gil Martins · Av. Gil Martins, 3144 – Três Andares – Teresina/PI · RV Engenharia
A4: 1. MÃO DE OBRA — DETALHAMENTO POR FUNCIONÁRIO
A5: Funcionário | B5: Função | C5: Diária (R$) | D5: Presença | E5: Valor do Dia (R$)
A6: Thiago | B6: Pedreiro | C6: =Parâmetros!$C$8 -> 200 | D6: 1 | E6: =C6*D6 -> 200
A7: Francisco | B7: Pedreiro | C7: =Parâmetros!$C$9 -> 160 | D7: 1 | E7: =C7*D7 -> 160
A8: Rufino | B8: Servente | C8: =Parâmetros!$C$10 -> 100 | D8: 1 | E8: =C8*D8 -> 100
A9: Carlos | B9: Servente | C9: =Parâmetros!$C$11 -> 100 | D9: 1 | E9: =C9*D9 -> 100
A10: SUBTOTAL — MÃO DE OBRA | C10: Diárias: | D10: =SUM(D6:D9) -> 4 | E10: =SUM(E6:E9) -> 560
A12: 2. ALIMENTAÇÃO E OUTROS CONSUMOS DO DIA
A13: Descrição | C13: Valor unitário (R$) | D13: Quantidade | E13: Valor Total (R$)
A14: Quentinhas fornecidas | C14: 18 | D14: 4 | E14: =C14*D14 -> 72
A15: Gelo | C15: 6 | D15: 2 | E15: =C15*D15 -> 12
A16: Entrega de quentinhas | C16: 10 | D16: 1 | E16: =C16*D16 -> 10
A17: SUBTOTAL — ALIMENTAÇÃO E OUTROS | E17: =SUM(E14:E16) -> 94
A19: 3. RESUMO DO DIA — QUINTA-FEIRA 10/09
A20: Total de diárias trabalhadas | E20: =D10 -> 4
A21: Quentinhas fornecidas (un.) | E21: =D14 -> 4
A22: Custo de mão de obra | E22: =E10 -> 560
A23: Custo de alimentação e outros | E23: =E17 -> 94
A24: TOTAL DO DIA | E24: =E22+E23 -> 654
A26: Observação: Quentinha com entrega (R$ 10,00)

Sheet Sexta 11-09
A1: SEXTA-FEIRA — 11/09/2026
A2: Obra: Selecta – Gil Martins · Av. Gil Martins, 3144 – Três Andares – Teresina/PI · RV Engenharia
A4: 1. MÃO DE OBRA — DETALHAMENTO POR FUNCIONÁRIO
A5: Funcionário | B5: Função | C5: Diária (R$) | D5: Presença | E5: Valor do Dia (R$)
A6: Thiago | B6: Pedreiro | C6: =Parâmetros!$C$8 -> 200 | D6: 1 | E6: =C6*D6 -> 200
A7: Francisco | B7: Pedreiro | C7: =Parâmetros!$C$9 -> 160 | D7: 1 | E7: =C7*D7 -> 160
A8: Rufino | B8: Servente | C8: =Parâmetros!$C$10 -> 100 | D8: 1 | E8: =C8*D8 -> 100
A9: Carlos | B9: Servente | C9: =Parâmetros!$C$11 -> 100 | D9: 1 | E9: =C9*D9 -> 100
A10: SUBTOTAL — MÃO DE OBRA | C10: Diárias: | D10: =SUM(D6:D9) -> 4 | E10: =SUM(E6:E9) -> 560
A12: 2. ALIMENTAÇÃO E OUTROS CONSUMOS DO DIA
A13: Descrição | C13: Valor unitário (R$) | D13: Quantidade | E13: Valor Total (R$)
A14: Quentinhas fornecidas | C14: 18 | D14: 4 | E14: =C14*D14 -> 72
A15: Gelo | C15: 6 | D15: 2 | E15: =C15*D15 -> 12
A16: Entrega de quentinhas | C16: 10 | D16: 1 | E16: =C16*D16 -> 10
A17: SUBTOTAL — ALIMENTAÇÃO E OUTROS | E17: =SUM(E14:E16) -> 94
A19: 3. RESUMO DO DIA — SEXTA-FEIRA 11/09
A20: Total de diárias trabalhadas | E20: =D10 -> 4
A21: Quentinhas fornecidas (un.) | E21: =D14 -> 4
A22: Custo de mão de obra | E22: =E10 -> 560
A23: Custo de alimentação e outros | E23: =E17 -> 94
A24: TOTAL DO DIA | E24: =E22+E23 -> 654
A26: Observação: Quentinha com entrega (R$ 10,00). Encerramento da semana na sexta-feira

Sheet Resumo Semanal
A1: RESUMO GERAL DA SEMANA — 07/09 A 11/09/2026
A2: Obra: Selecta – Gil Martins · Av. Gil Martins, 3144 – Três Andares – Teresina/PI · RV Engenharia
A4: 1. FECHAMENTO POR DIA
A5: Dia | B5: Data | C5: Diárias | D5: Mão de Obra (R$) | E5: Quentinhas (un.) | F5: Alim. e outros (R$) | G5: Total do Dia (R$)
A6: Segunda | B6: 46272 | C6: ='Segunda 07-09'!$E$17 -> 1 | D6: ='Segunda 07-09'!$E$19 -> 200 | E6: ='Segunda 07-09'!$E$18 -> 0 | F6: ='Segunda 07-09'!$E$20 -> 0 | G6: ='Segunda 07-09'!$E$21 -> 200
A7: Terça | B7: 46273 | C7: ='Terça 08-09'!$E$19 -> 4 | D7: ='Terça 08-09'!$E$21 -> 560 | E7: ='Terça 08-09'!$E$20 -> 4 | F7: ='Terça 08-09'!$E$22 -> 84 | G7: ='Terça 08-09'!$E$23 -> 644
A8: Quarta | B8: 46274 | C8: ='Quarta 09-09'!$E$19 -> 4 | D8: ='Quarta 09-09'!$E$21 -> 560 | E8: ='Quarta 09-09'!$E$20 -> 4 | F8: ='Quarta 09-09'!$E$22 -> 84 | G8: ='Quarta 09-09'!$E$23 -> 644
A9: Quinta | B9: 46275 | C9: ='Quinta 10-09'!$E$20 -> 4 | D9: ='Quinta 10-09'!$E$22 -> 560 | E9: ='Quinta 10-09'!$E$21 -> 4 | F9: ='Quinta 10-09'!$E$23 -> 94 | G9: ='Quinta 10-09'!$E$24 -> 654
A10: Sexta | B10: 46276 | C10: ='Sexta 11-09'!$E$20 -> 4 | D10: ='Sexta 11-09'!$E$22 -> 560 | E10: ='Sexta 11-09'!$E$21 -> 4 | F10: ='Sexta 11-09'!$E$23 -> 94 | G10: ='Sexta 11-09'!$E$24 -> 654
A11: TOTAL DA SEMANA | C11: =SUM(C6:C10) -> 17 | D11: =SUM(D6:D10) -> 2440 | E11: =SUM(E6:E10) -> 16 | F11: =SUM(F6:F10) -> 356 | G11: =SUM(G6:G10) -> 2796
A13: 2. GASTOS POR FUNCIONÁRIO
A14: Funcionário | B14: Função | C14: Diária (R$) | D14: Diárias na Semana | G14: Total a Pagar (R$)
A15: Thiago | B15: Pedreiro | C15: =Parâmetros!$C$8 -> 200 | D15: ='Segunda 07-09'!$D$6+'Terça 08-09'!$D$6+'Quarta 09-09'!$D$6+'Quinta 10-09'!$D$6+'Sexta 11-09'!$D$6 -> 5 | G15: =C15*D15 -> 1000
A16: Francisco | B16: Pedreiro | C16: =Parâmetros!$C$9 -> 160 | D16: ='Segunda 07-09'!$D$7+'Terça 08-09'!$D$7+'Quarta 09-09'!$D$7+'Quinta 10-09'!$D$7+'Sexta 11-09'!$D$7 -> 4 | G16: =C16*D16 -> 640
A17: Rufino | B17: Servente | C17: =Parâmetros!$C$10 -> 100 | D17: ='Segunda 07-09'!$D$8+'Terça 08-09'!$D$8+'Quarta 09-09'!$D$8+'Quinta 10-09'!$D$8+'Sexta 11-09'!$D$8 -> 4 | G17: =C17*D17 -> 400
A18: Carlos | B18: Servente | C18: =Parâmetros!$C$11 -> 100 | D18: ='Segunda 07-09'!$D$9+'Terça 08-09'!$D$9+'Quarta 09-09'!$D$9+'Quinta 10-09'!$D$9+'Sexta 11-09'!$D$9 -> 4 | G18: =C18*D18 -> 400
A19: TOTAL — MÃO DE OBRA DA SEMANA | D19: =SUM(D15:D18) -> 17 | G19: =SUM(G15:G18) -> 2440
A21: 3. GASTOS COM QUENTINHAS — SEPARADO POR VALOR UNITÁRIO (E OUTROS CONSUMOS)
A22: Valor unitário / item | B22: Dias em que foi usado | E22: Quantidade (un.) | G22: Custo (R$)
A23: 18 | B23: 08/09, 09/09, 10/09, 11/09 | E23: ='Terça 08-09'!$D$14+'Quarta 09-09'!$D$14+'Quinta 10-09'!$D$14+'Sexta 11-09'!$D$14 -> 16 | G23: ='Terça 08-09'!$E$14+'Quarta 09-09'!$E$14+'Quinta 10-09'!$E$14+'Sexta 11-09'!$E$14 -> 288
A24: Gelo | B24: 08/09, 09/09, 10/09, 11/09 (8 × R$ 6,00) | E24: 8 | G24: ='Terça 08-09'!$E$15+'Quarta 09-09'!$E$15+'Quinta 10-09'!$E$15+'Sexta 11-09'!$E$15 -> 48
A25: Entrega de quentinhas | B25: 10/09, 11/09 (2 × R$ 10,00) | E25: 2 | G25: ='Quinta 10-09'!$E$16+'Sexta 11-09'!$E$16 -> 20
A26: TOTAL — ALIMENTAÇÃO E OUTROS | E26: =SUM(E23:E23) -> 16 | G26: =SUM(G23:G25) -> 356
A28: 4. GASTO GERAL DA SEMANA
A29: Total de mão de obra | G29: =G19 -> 2440
A30: Total de alimentação e outros | G30: =G26 -> 356
A31: GASTO GERAL DA SEMANA | G31: =G29+G30 -> 2796
A33: 5. ACUMULADO DA OBRA
A34: Período | C34: Diárias | D34: Mão de Obra (R$) | E34: Quentinhas (un.) | F34: Alim. e outros (R$) | G34: Total (R$)
A35: Semana 1 — 20/07 a 25/07 | C35: 16 | D35: 2340 | E35: 12 | F35: 264 | G35: 2604
A36: Semana 2 — 27/07 a 31/07 | C36: 19 | D36: 2370 | E36: 19 | F36: 334 | G36: 2704
A37: Semana 3 — 03/08 a 07/08 | C37: 14 | D37: 2360 | E37: 14 | F37: 246 | G37: 2606
A38: Semana 4 — 10/08 a 14/08 | C38: 11.5 | D38: 2025 | E38: 13 | F38: 246 | G38: 2271
A39: Semana 5 — 17/08 a 20/08 | C39: 12 | D39: 1960 | E39: 12 | F39: 216 | G39: 2176
A40: Semana 6 — 24/08 a 28/08 | C40: 9 | D40: 1800 | E40: 9 | F40: 186 | G40: 1986
A41: Semana 7 — 31/08 a 04/09 | C41: 10 | D41: 1700 | E41: 10 | F41: 188 | G41: 1888
A42: Semana 8 — 07/09 a 11/09 | C42: =C11 -> 17 | D42: =D11 -> 2440 | E42: =E11 -> 16 | F42: =F11 -> 356 | G42: =G11 -> 2796
A43: TOTAL ACUMULADO DA OBRA | C43: =SUM(C35:C42) -> 108.5 | D43: =SUM(D35:D42) -> 16995 | E43: =SUM(E35:E42) -> 105 | F43: =SUM(F35:F42) -> 2036 | G43: =SUM(G35:G42) -> 19031
A45: Notas da semana: 07/09 — Feriado (Independência): expediente até meio-dia, diária integral e sem quentinha; 08/09 — Entrada de Francisco (pedreiro, R$ 160,00), Rufino e Carlos (serventes, R$ 100,00). Início da compra de gelo; 10/09 — Quentinha com entrega (R$ 10,00); 11/09 — Quentinha com entrega (R$ 10,00). Encerramento da semana na sexta-feira. Constam apenas os funcionários com presença na semana. Os totais de mão de obra dos blocos 1 e 2 devem ser idênticos.
